pymygdala/__init__.py
pymygdala/_version.py
pymygdala/commands.py
pymygdala/models.py
pymygdala-0.2.2.dist-info/DESCRIPTION.rst
pymygdala-0.2.2.dist-info/METADATA
pymygdala-0.2.2.dist-info/RECORD
pymygdala-0.2.2.dist-info/WHEEL
pymygdala-0.2.2.dist-info/entry_points.txt
pymygdala-0.2.2.dist-info/metadata.json
pymygdala-0.2.2.dist-info/top_level.txt
tests/__init__.py
tests/test_stub.py
