Metadata-Version: 2.0
Name: pymygdala
Version: 0.2.2
Summary: Pymygdala: Archive messaging for Python
Home-page: https://open-bitbucket.nrao.edu/projects/SSA/repos/pymygdala
Author: Daniel K Lyons
Author-email: dlyons@nrao.edu
License: GPL
Platform: UNKNOWN
Classifier: Development Status :: 3 - Alpha
Classifier: Intended Audience :: Developers
Classifier: Topic :: Software Development :: Build Tools
Classifier: License :: OSI Approved :: GNU General Public License v2 (GPLv2)
Classifier: Programming Language :: Python :: 2.7
Classifier: Programming Language :: Python :: 3
Classifier: Programming Language :: Python :: 3.5
Requires-Dist: pika (==0.10.0)
Requires-Dist: pycapo (==0.1.1)
Requires-Dist: python-dateutil (==2.6.0)
Requires-Dist: simplejson (==3.11.1)
